subs2vec/__init__.py
subs2vec/analogies.py
subs2vec/clean_subs.py
subs2vec/clean_wiki.py
subs2vec/count_words.py
subs2vec/deduplicate.py
subs2vec/download.py
subs2vec/frequencies.py
subs2vec/inferential_stats.py
subs2vec/lang_compile.py
subs2vec/lang_evaluate.py
subs2vec/lookup.py
subs2vec/make_table.py
subs2vec/norms.py
subs2vec/paper_plots.py
subs2vec/paper_stats.py
subs2vec/paper_table.py
subs2vec/plots.py
subs2vec/similarities.py
subs2vec/train_model.py
subs2vec/utensils.py
subs2vec/vecs.py
subs2vec/datasets/norms_table.tsv
subs2vec/datasets/analogies/cs-analogies-svoboda.tsv
subs2vec/datasets/analogies/de-analogies-semrel.tsv
subs2vec/datasets/analogies/de-semantic-google.tsv
subs2vec/datasets/analogies/de-syntactic-google.tsv
subs2vec/datasets/analogies/el-semantic_nocountries-google.tsv
subs2vec/datasets/analogies/el-syntactic-google.tsv
subs2vec/datasets/analogies/en-analogies-bless.tsv
subs2vec/datasets/analogies/en-analogies-semrel.tsv
subs2vec/datasets/analogies/en-semantic-google.tsv
subs2vec/datasets/analogies/en-semantic_no_countries-google.tsv
subs2vec/datasets/analogies/en-syntactic-google.tsv
subs2vec/datasets/analogies/fi-analogies-venekoski.tsv
subs2vec/datasets/analogies/fr-semantic-google.tsv
subs2vec/datasets/analogies/fr-syntactic-google.tsv
subs2vec/datasets/analogies/he-semantic_no_countries-google.tsv
subs2vec/datasets/analogies/he-syntactic-google.tsv
subs2vec/datasets/analogies/hi-semantic-google.tsv
subs2vec/datasets/analogies/hi-syntactic-google.tsv
subs2vec/datasets/analogies/it-semantic-google.tsv
subs2vec/datasets/analogies/it-syntactic-google.tsv
subs2vec/datasets/analogies/nl-semantic_nocountries-google.tsv
subs2vec/datasets/analogies/nl-syntactic-google.tsv
subs2vec/datasets/analogies/pl-semantic-google.tsv
subs2vec/datasets/analogies/pl-syntactic-google.tsv
subs2vec/datasets/analogies/pt-semantic-google.tsv
subs2vec/datasets/analogies/pt-syntactic-google.tsv
subs2vec/datasets/analogies/zh-semantic-google.tsv
subs2vec-0.9.6.dist-info/LICENSE.md
subs2vec-0.9.6.dist-info/METADATA
subs2vec-0.9.6.dist-info/WHEEL
subs2vec-0.9.6.dist-info/top_level.txt
subs2vec-0.9.6.dist-info/RECORD
