Metadata-Version: 2.1
Name: subs2vec
Version: 0.9.6
Summary: subs2vec module
Home-page: https://github.com/jvparidon/subs2vec/
Author: Jeroen van Paridon & Bill Thompson
Author-email: j.v.paridon@gmail.com
License: MIT
Platform: UNKNOWN
Classifier: Programming Language :: Python :: 3
Classifier: License :: OSI Approved :: MIT License
Requires-Python: >=3.6
Requires-Dist: numpy
Requires-Dist: scipy
Requires-Dist: pandas (>=1.0)
Requires-Dist: lxml
Requires-Dist: joblib
Requires-Dist: matplotlib
Requires-Dist: seaborn (>=0.10)
Requires-Dist: scikit-learn
Requires-Dist: psutil
Requires-Dist: pymc3 (>=3.8)
